{
  "$id": "https://contracts.cloudmorph.io/v0.1/redaction-rule.schema.json",
  "$schema": "http://json-schema.org/draft-07/schema#",
  "title": "Redaction Rule",
  "description": "A single field-level redaction. Multiple rules combine into a redact decision. The MCP server applies redactions to the response before returning to the agent.",
  "type": "object",
  "additionalProperties": false,
  "required": ["schemaVersion", "ruleId", "fieldPath", "redactionMode"],
  "properties": {
    "schemaVersion": {
      "type": "string",
      "pattern": "^v[0-9]+\\.[0-9]+$"
    },
    "ruleId": { "type": "string" },
    "fieldPath": {
      "type": "string",
      "description": "JSON Pointer (RFC 6901) selecting the field to redact. Wildcards via /*/ for arrays."
    },
    "redactionMode": {
      "type": "string",
      "enum": ["mask", "drop", "hash", "tokenize"],
      "description": "mask: replace with '***'. drop: remove field entirely. hash: replace with sha256. tokenize: replace with reversible token (requires KMS)."
    },
    "tokenizationKeyId": {
      "type": "string",
      "description": "When mode=tokenize, the KMS key id to use."
    },
    "appliesTo": {
      "type": "array",
      "description": "Action patterns (glob) the rule applies to. Empty = applies to all.",
      "items": { "type": "string" }
    },
    "x_meta": {
      "type": "object",
      "additionalProperties": true
    }
  }
}
